omnibusx_sdk/__init__.py
omnibusx_sdk/api_client.py
omnibusx_sdk/models.py
omnibusx_sdk-0.1.2.dist-info/METADATA
omnibusx_sdk-0.1.2.dist-info/WHEEL
omnibusx_sdk-0.1.2.dist-info/RECORD
